aipalettenlp/__init__.py
aipalettenlp/text_cleaning.py
aipalettenlp/tokenizer.py
aipalettenlp-0.0.7.dist-info/LICENSE
aipalettenlp-0.0.7.dist-info/METADATA
aipalettenlp-0.0.7.dist-info/WHEEL
aipalettenlp-0.0.7.dist-info/top_level.txt
aipalettenlp-0.0.7.dist-info/RECORD
