Metadata-Version: 2.1
Name: aipalettenlp
Version: 0.0.7
Summary: Ai Palette NLP toolkit
Home-page: https://github.com/ng-cube/nlp_library
Author: Jingfang Huang
Author-email: jingfang@aipalette.com
Project-URL: Bug Tracker, https://github.com/ng-cube/nlp_library/issues
Classifier: Programming Language :: Python :: 3
Classifier: License :: OSI Approved :: MIT License
Classifier: Operating System :: OS Independent
Requires-Python: >=3.8
License-File: LICENSE
